owrf1d/_core.cpython-313-darwin.so
owrf1d/_core.pxd
owrf1d/_core.c
owrf1d/flags.py
owrf1d/__init__.py
owrf1d/_core.pyx
owrf1d/filter.py
owrf1d-1.0.4.dist-info/RECORD
owrf1d-1.0.4.dist-info/WHEEL
owrf1d-1.0.4.dist-info/top_level.txt
owrf1d-1.0.4.dist-info/METADATA
owrf1d-1.0.4.dist-info/licenses/LICENSE
