Metadata-Version: 2.4
Name: owrf1d
Version: 1.0.4
Summary: Online Window Regression Filter 1D (fast-cython, parameterless)
License-Expression: MIT
Project-URL: Homepage, https://github.com/TovarnovM/owrf1d
Project-URL: Repository, https://github.com/TovarnovM/owrf1d
Project-URL: Issues, https://github.com/TovarnovM/owrf1d/issues
Requires-Python: >=3.10
License-File: LICENSE
Requires-Dist: cloudpickle>=2.2
Provides-Extra: dev
Requires-Dist: pytest>=7.0; extra == "dev"
Requires-Dist: ruff>=0.4; extra == "dev"
Requires-Dist: Cython>=3.0; extra == "dev"
Requires-Dist: build; extra == "dev"
Requires-Dist: twine; extra == "dev"
Provides-Extra: examples
Requires-Dist: matplotlib>=3.8; extra == "examples"
Requires-Dist: numpy>=1.26; extra == "examples"
Dynamic: license-file
